deskframe/__init__.py
deskframe/deskframe.py
deskframe/Tools/Menu.py
deskframe/Tools/ToolBar.py
deskframe/Tools/VideoFrame.py
deskframe/Tools/__init__.py
deskframe/Tools/font.py
deskframe/values/Symbols.py
deskframe/values/Values.py
deskframe/values/__init__.py
deskframe/views/ViewBuilder.py
deskframe/views/__init__.py
deskframe/views/dialogBuilder.py
deskframe/views/notification.py
deskframe/views/rootBuilder.py
deskframe/views/toast.py
deskframe-1.0.1.dist-info/METADATA
deskframe-1.0.1.dist-info/WHEEL
deskframe-1.0.1.dist-info/entry_points.txt
deskframe-1.0.1.dist-info/top_level.txt
deskframe-1.0.1.dist-info/RECORD
