Metadata-Version: 2.1
Name: deskframe
Version: 1.0.1
Summary: DeskFrame is a Python library that simplifies the process of creating graphical user interfaces (GUIs) using XML for layout design and Python for backend logic. 
Home-page: https://github.com/SriBalaji2112/DeskFrame/
Author: BalajiSanthanam
Author-email: sribalaji2112@gmail.com
License: BSD 3-Clause License
Keywords: GUI tkinter customtkinter ctk tk python application network api ui gui deskframe app desktop create gui
Classifier: Development Status :: 4 - Beta
Classifier: Environment :: Win32 (MS Windows)
Classifier: Environment :: X11 Applications
Classifier: Environment :: MacOS X
Classifier: Intended Audience :: Developers
Classifier: License :: OSI Approved :: MIT License
Classifier: Operating System :: OS Independent
Classifier: Programming Language :: Python :: 3
Classifier: Programming Language :: Python :: 3.1
Classifier: Programming Language :: Python :: 3.2
Classifier: Programming Language :: Python :: 3.3
Classifier: Programming Language :: Python :: 3.4
Classifier: Programming Language :: Python :: 3.5
Classifier: Programming Language :: Python :: 3.6
Classifier: Programming Language :: Python :: 3.7
Classifier: Programming Language :: Python :: 3.8
Classifier: Programming Language :: Python :: 3.9
Classifier: Programming Language :: Python :: 3.10
Classifier: Programming Language :: Python :: 3.11
Classifier: Programming Language :: Python :: 3.12
Requires-Dist: pymsgbox
Requires-Dist: pytweening>=1.0.4
Requires-Dist: pyscreeze>=0.1.21
Requires-Dist: pygetwindow>=0.0.5
Requires-Dist: customtkinter
Requires-Dist: Pillow
Requires-Dist: tkinter_webcam
Requires-Dist: plyer
